flask/__init__.py
flask/__main__.py
flask/_compat.py
flask/app.py
flask/blueprints.py
flask/cli.py
flask/config.py
flask/ctx.py
flask/debughelpers.py
flask/globals.py
flask/helpers.py
flask/logging.py
flask/sessions.py
flask/signals.py
flask/templating.py
flask/testing.py
flask/views.py
flask/wrappers.py
flask/json/__init__.py
flask/json/tag.py
flask_v1_0-1.0.5.dist-info/licenses/LICENSE.rst
flask_v1_0-1.0.5.dist-info/METADATA
flask_v1_0-1.0.5.dist-info/WHEEL
flask_v1_0-1.0.5.dist-info/entry_points.txt
flask_v1_0-1.0.5.dist-info/top_level.txt
flask_v1_0-1.0.5.dist-info/RECORD
