Metadata-Version: 2.4
Name: Flask-v1.0
Version: 1.0.5
Summary: A simple framework for building complex web applications.
Home-page: https://github.com/nottrobin/flask-v1.0
Author: Robin Winslow Morris
Author-email: robin@robinwinslow.co.uk
License: BSD-3-Clause
Project-URL: Documentation, https://github.com/nottrobin/flask-v1.0/blob/main/README.md
Project-URL: Code, https://github.com/nottrobin/flask-v1.0
Requires-Python: >=2.7, !=3.0.*, !=3.1.*, !=3.2.*, !=3.3.*
License-File: LICENSE.rst
Requires-Dist: Werkzeug<3,>=0.14
Requires-Dist: Jinja2<3.1,>=2.4
Requires-Dist: itsdangerous<2.1,>=0.21
Requires-Dist: click>=2.0
Dynamic: author
Dynamic: author-email
Dynamic: description
Dynamic: description-content-type
Dynamic: home-page
Dynamic: license
Dynamic: license-file
Dynamic: project-url
Dynamic: requires-dist
Dynamic: requires-python
Dynamic: summary
